<?xml version="1.0" encoding="UTF-8"?><maryxml xmlns="http://mary.dfki.de/2002/MaryXML" xmlns:xsi="http://www.w3.org/2001/XMLSchema-instance" version="0.4" xml:lang="nls">
<p>
<s>
<phrase>
<boundary breakindex="2" duration="100"/>
<t accent="L+H*" g2p_method="lexicon" ph="ih - n - t - er - m - ih - n - ih - s - t - iy - r - iy - ax - l" pos="content">
Inter-ministerial
<syllable ph="ih">
<ph p="ih"/>
</syllable>
<syllable ph="n">
<ph p="n"/>
</syllable>
<syllable ph="t">
<ph p="t"/>
</syllable>
<syllable ph="er">
<ph p="er"/>
</syllable>
<syllable ph="m">
<ph p="m"/>
</syllable>
<syllable ph="ih">
<ph p="ih"/>
</syllable>
<syllable ph="n">
<ph p="n"/>
</syllable>
<syllable ph="ih">
<ph p="ih"/>
</syllable>
<syllable ph="s">
<ph p="s"/>
</syllable>
<syllable ph="t">
<ph p="t"/>
</syllable>
<syllable ph="iy">
<ph p="iy"/>
</syllable>
<syllable ph="r">
<ph p="r"/>
</syllable>
<syllable ph="iy">
<ph p="iy"/>
</syllable>
<syllable ph="ax">
<ph p="ax"/>
</syllable>
<syllable ph="l">
<ph p="l"/>
</syllable>
</t>
<t accent="L+H*" g2p_method="lexicon" ph="ae - n - d" pos="content">
and
<syllable ph="ae">
<ph p="ae"/>
</syllable>
<syllable ph="n">
<ph p="n"/>
</syllable>
<syllable ph="d">
<ph p="d"/>
</syllable>
</t>
<t accent="L+H*" g2p_method="lexicon" ph="ih - n - t - er - ey - jh - ax - n - s - iy" pos="content">
inter-agency
<syllable ph="ih">
<ph p="ih"/>
</syllable>
<syllable ph="n">
<ph p="n"/>
</syllable>
<syllable ph="t">
<ph p="t"/>
</syllable>
<syllable ph="er">
<ph p="er"/>
</syllable>
<syllable ph="ey">
<ph p="ey"/>
</syllable>
<syllable ph="jh">
<ph p="jh"/>
</syllable>
<syllable ph="ax">
<ph p="ax"/>
</syllable>
<syllable ph="n">
<ph p="n"/>
</syllable>
<syllable ph="s">
<ph p="s"/>
</syllable>
<syllable ph="iy">
<ph p="iy"/>
</syllable>
</t>
<t accent="!H*" g2p_method="lexicon" ph="k - ax - m - ih - t - iy - z" pos="content">
committees
<syllable ph="k">
<ph p="k"/>
</syllable>
<syllable ph="ax">
<ph p="ax"/>
</syllable>
<syllable ph="m">
<ph p="m"/>
</syllable>
<syllable ph="ih">
<ph p="ih"/>
</syllable>
<syllable ph="t">
<ph p="t"/>
</syllable>
<syllable ph="iy">
<ph p="iy"/>
</syllable>
<syllable ph="z">
<ph p="z"/>
</syllable>
</t>
<t pos="$PUNCT">
.
</t>
<boundary breakindex="5" tone="L-L%"/>
</phrase>
</s>
</p>
</maryxml>
